README.rst
pyproject.toml
setup.py
objr/__init__.py
objr.egg-info/PKG-INFO
objr.egg-info/SOURCES.txt
objr.egg-info/dependency_links.txt
objr.egg-info/requires.txt
objr.egg-info/top_level.txt
objr.egg-info/zip-safe