Metadata-Version: 2.1
Name: objr
Version: 170
Summary: reactor
Author-email: Bart Thate <rssbotd@gmail.com>
License: Public Domain
Project-URL: home, https://pypi.org/rssbotd/objr
Project-URL: bugs, https://github.com/rssbotd/objr/issues
Project-URL: source, https://github.com/rssbotd/objr
Classifier: Development Status :: 3 - Alpha
Classifier: License :: Public Domain
Classifier: Operating System :: Unix
Classifier: Programming Language :: Python
Classifier: Topic :: Utilities
